multiworkerqueue/__init__.py
multiworkerqueue/multi_worker_queue.py
multiworkerqueue-0.0.1.dist-info/LICENSE
multiworkerqueue-0.0.1.dist-info/METADATA
multiworkerqueue-0.0.1.dist-info/WHEEL
multiworkerqueue-0.0.1.dist-info/top_level.txt
multiworkerqueue-0.0.1.dist-info/RECORD
