Metadata-Version: 2.1
Name: multiworkerqueue
Version: 0.0.1
Summary: python worker queue supporting multi-producer and multi-consumer threads.
Author-email: Reznic <reznic.tal@gmail.com>
Project-URL: Homepage, https://github.com/Reznic/MultiWorkerQueue
Project-URL: Bug Tracker, https://github.com/Reznic/MultiWorkerQueue/issues
Classifier: Programming Language :: Python :: 3
Classifier: License :: OSI Approved :: MIT License
Classifier: Operating System :: OS Independent
Requires-Python: >=3.7
License-File: LICENSE
